idm_mobile_client_py/__init__.py
idm_mobile_client_py/client.py
idm_mobile_client_py/exceptions.py
idm_mobile_client_py-0.0.4.dist-info/LICENSE.md
idm_mobile_client_py-0.0.4.dist-info/METADATA
idm_mobile_client_py-0.0.4.dist-info/WHEEL
idm_mobile_client_py-0.0.4.dist-info/top_level.txt
idm_mobile_client_py-0.0.4.dist-info/RECORD
